disposition/__init__.py
disposition/core.py
disposition/elements/canvas.py
disposition/elements/core.py
disposition-0.1.4.dist-info/LICENSE
disposition-0.1.4.dist-info/METADATA
disposition-0.1.4.dist-info/WHEEL
disposition-0.1.4.dist-info/RECORD
