Metadata-Version: 2.1
Name: disposition
Version: 0.1.4
Summary: Framework for generating reports and plots with flexible and precise layouts
Home-page: https://disposition.readthedocs.io
License: MIT
Keywords: reports,layout,plots
Author: Kenneth Trelborg Vestergaard
Author-email: mortencombat@fastmail.com
Requires-Python: >=3.9,<4.0
Classifier: Development Status :: 3 - Alpha
Classifier: Intended Audience :: Developers
Classifier: Intended Audience :: Science/Research
Classifier: License :: OSI Approved :: MIT License
Classifier: Operating System :: OS Independent
Classifier: Programming Language :: Python :: 3
Classifier: Programming Language :: Python :: 3.9
Classifier: Programming Language :: Python :: 3.10
Classifier: Programming Language :: Python :: 3.11
Classifier: Programming Language :: Python :: 3.12
Requires-Dist: stretchable (>=1.0.0b3,<2.0.0)
Project-URL: Documentation, https://disposition.readthedocs.io
Project-URL: Repository, https://github.com/mortencombat/disposition
